__init__.py
scrapers/__init__.py
scrapers/base.py
scrapers/senate.py
utils/__init__.py
utils/data.py
utils/session.py
congress_transactions-0.0.1.dist-info/LICENSE
congress_transactions-0.0.1.dist-info/METADATA
congress_transactions-0.0.1.dist-info/WHEEL
congress_transactions-0.0.1.dist-info/top_level.txt
congress_transactions-0.0.1.dist-info/RECORD
